invenio_workflows/__init__.py
invenio_workflows/acl.py
invenio_workflows/api.py
invenio_workflows/bundles.py
invenio_workflows/client.py
invenio_workflows/config.py
invenio_workflows/definitions.py
invenio_workflows/engine.py
invenio_workflows/errors.py
invenio_workflows/logger.py
invenio_workflows/manage.py
invenio_workflows/models.py
invenio_workflows/registry.py
invenio_workflows/signals.py
invenio_workflows/utils.py
invenio_workflows/version.py
invenio_workflows/worker_engine.py
invenio_workflows/worker_result.py
invenio_workflows/actions/__init__.py
invenio_workflows/actions/approval.py
invenio_workflows/static/css/workflows/workflows.css
invenio_workflows/static/js/workflows/common.js
invenio_workflows/static/js/workflows/details.js
invenio_workflows/static/js/workflows/details_actions.js
invenio_workflows/static/js/workflows/details_actions_buttons.js
invenio_workflows/static/js/workflows/details_page.js
invenio_workflows/static/js/workflows/details_preview.js
invenio_workflows/static/js/workflows/details_preview_menu.js
invenio_workflows/static/js/workflows/holdingpen.js
invenio_workflows/static/js/workflows/init.js
invenio_workflows/static/js/workflows/maintable.js
invenio_workflows/static/js/workflows/pagination.js
invenio_workflows/static/js/workflows/perpage_menu.js
invenio_workflows/static/js/workflows/selection.js
invenio_workflows/static/js/workflows/sort_menu.js
invenio_workflows/static/js/workflows/tags.js
invenio_workflows/static/js/workflows/tags_menu.js
invenio_workflows/static/js/workflows/actions/approval.js
invenio_workflows/static/js/workflows/actions/init.js
invenio_workflows/static/js/workflows/templates/alert.mustache
invenio_workflows/static/js/workflows/templates/pagination.mustache
invenio_workflows/tasks/__init__.py
invenio_workflows/tasks/logic_tasks.py
invenio_workflows/tasks/sample_tasks.py
invenio_workflows/tasks/simplified_data_tasks.py
invenio_workflows/tasks/workflows_tasks.py
invenio_workflows-0.1.2.dist-info/top_level.txt
invenio_workflows-0.1.2.dist-info/METADATA
invenio_workflows-0.1.2.dist-info/DESCRIPTION.rst
invenio_workflows-0.1.2.dist-info/metadata.json
invenio_workflows-0.1.2.dist-info/WHEEL
invenio_workflows-0.1.2.dist-info/RECORD
